har2postman/__init__.py
har2postman/cli.py
har2postman/common.py
har2postman/har2postman.py
har2postman-0.1.3.dist-info/entry_points.txt
har2postman-0.1.3.dist-info/LICENSE
har2postman-0.1.3.dist-info/WHEEL
har2postman-0.1.3.dist-info/METADATA
har2postman-0.1.3.dist-info/RECORD
